flask_beginner/__init__.py
flask_beginner/beginner.py
Flask_Beginner-0.0.4.dist-info/LICENSE
Flask_Beginner-0.0.4.dist-info/METADATA
Flask_Beginner-0.0.4.dist-info/WHEEL
Flask_Beginner-0.0.4.dist-info/entry_points.txt
Flask_Beginner-0.0.4.dist-info/top_level.txt
Flask_Beginner-0.0.4.dist-info/RECORD
