Metadata-Version: 2.1
Name: Flask-Beginner
Version: 0.0.4
Summary: a quick project directory maker for flask
Home-page: https://github.com/r1cardohj/flask-beginner
Author: r1cardohj
License: MIT
Keywords: flask extension development
Platform: UNKNOWN
Classifier: Development Status :: 3 - Alpha
Classifier: Programming Language :: Python :: 3
Requires-Dist: flask
Provides-Extra: all
Requires-Dist: flask-login ; extra == 'all'
Requires-Dist: flask-wtf ; extra == 'all'
Requires-Dist: flask-sqlalchemy ; extra == 'all'
Requires-Dist: Flask-Migrate ; extra == 'all'
